gimmebio.kmers-0.4.8-py3.6-nspkg.pth
gimmebio/kmers/__init__.py
gimmebio/kmers/cli.py
gimmebio/kmers/gmers.py
gimmebio/kmers/kmer_stats.py
gimmebio/kmers/kmers.py
gimmebio/kmers/min_sparse_kmers.py
gimmebio/kmers/rabin_kmers.py
gimmebio/kmers/clustering/__init__.py
gimmebio/kmers/clustering/cli.py
gimmebio/kmers/clustering/eval_clustering.py
gimmebio/kmers/clustering/kd_rft_cover.py
gimmebio/kmers/clustering/radial_cover.py
gimmebio.kmers-0.4.8.dist-info/METADATA
gimmebio.kmers-0.4.8.dist-info/RECORD
gimmebio.kmers-0.4.8.dist-info/WHEEL
gimmebio.kmers-0.4.8.dist-info/namespace_packages.txt
gimmebio.kmers-0.4.8.dist-info/top_level.txt
